file_sanitizer/__init__.py
file_sanitizer/backup.py
file_sanitizer/cli.py
file_sanitizer/csv_sanitizer.py
file_sanitizer/env_sanitizer.py
file_sanitizer/json_sanitizer.py
file_sanitizer/utils.py
file_sanitizer/yaml_sanitizer.py
file_sanitizer-0.1.1.dist-info/licenses/LICENSE
file_sanitizer-0.1.1.dist-info/METADATA
file_sanitizer-0.1.1.dist-info/WHEEL
file_sanitizer-0.1.1.dist-info/entry_points.txt
file_sanitizer-0.1.1.dist-info/top_level.txt
file_sanitizer-0.1.1.dist-info/RECORD
