Metadata-Version: 2.4
Name: file-sanitizer
Version: 0.1.1
Summary: A powerful file sanitizer for env, YAML, JSON, CSV
Author-email: "V. Arvindh Kumar" <arvindhvetri@gmail.com>
License-Expression: MIT
Keywords: sanitizer,data-cleaning,env,yaml,json,csv,security
Classifier: Development Status :: 4 - Beta
Classifier: Intended Audience :: Developers
Classifier: Operating System :: OS Independent
Classifier: Programming Language :: Python :: 3
Classifier: Programming Language :: Python :: 3.8
Classifier: Programming Language :: Python :: 3.9
Classifier: Programming Language :: Python :: 3.10
Classifier: Programming Language :: Python :: 3.11
Classifier: Topic :: Security
Classifier: Topic :: Utilities
Requires-Python: >=3.8
License-File: LICENSE
Requires-Dist: PyYAML
Requires-Dist: pandas
Requires-Dist: cryptography
Dynamic: license-file
